{
    "id": "string",
    "title": "string",
    "subtitle": "string",
    "intro": {
        "title": "string",
        "full_name": "string",
        "curator": "string",
        "venue": "string",
        "time": "string",
        "description": "long string",
        "sound": [{
            "name": "string",
            "type": "soundcloud or soundfile",
            "url": "LINK"
        }], 
        "category":["category_id"],
        "youtube_links": ["url"],
        "hyperlinks": [{
            "link": "url",
            "name": "string"
        }]
    },
    "show_room": [{
        "name":"string",
        "url": "string"
    }],
    "creation": [{
        "title": "string",
        "creator": "string",
        "description": "long string",
        "media": [{
            "type": "photo or video",
            "url":"LINK"
        }],
        "sound": [{
            "name": "string",
            "type": "soundcloud or soundfile",
            "url": "LINK"
        }],
        "category":["category_id"], 
        "hyperlinks": [{
            "link": "url",
            "name": "string"
        }]
    }],
    "about": {
        "curator": [{
            "name":"string",
            "description": "long string",
            "media": ["LINK"], 
            "hyperlinks": [{
                "link": "url",
                "name": "string"
            }]
        }],
        "artist": [{
            "name":"string",
            "description": "long string",
            "media": ["LINK"], 
            "hyperlinks": [{
                "link": "url",
                "name": "string"
            }]
        }]
    }
}